<?xml version="1.0" encoding="UTF-8"?>
<objects serializationModel="Studio.02.00.00">
	<object class="EncodingSetting" id="{9fd23929-a434-4fc3-9185-932e2c34f23f}">
		<property name="encodingFormat">
			<value>3</value>
		</property>
		<property name="quality">
			<value>37</value>
		</property>
		<relationship name="platform">
			<destination>{aedd4987-1c9a-4a84-996a-de001947c466}</destination>
		</relationship>
		<relationship name="encodable">
			<destination>{aedd4987-1c9a-4a84-996a-de001947c466}</destination>
		</relationship>
	</object>
</objects>
